{
  "scanned_at": "2026-02-07T19:37:52.493Z",
  "directory": "./src/components/ai-elements",
  "total_files": 50,
  "index_exports": [
    "conversation",
    "message",
    "prompt-input",
    "reasoning",
    "tool",
    "sources",
    "chain-of-thought",
    "suggestion",
    "shimmer",
    "attachments",
    "image",
    "audio-player",
    "speech-input",
    "code-block",
    "artifact",
    "artifact-panel",
    "markdown",
    "toolbar",
    "controls",
    "context",
    "panel",
    "agent",
    "canvas",
    "checkpoint",
    "commit",
    "confirmation",
    "connection",
    "edge",
    "environment-variables",
    "file-tree",
    "inline-citation",
    "jsx-preview",
    "mic-selector",
    "model-selector",
    "node",
    "open-in-chat",
    "package-info",
    "persona",
    "plan",
    "queue",
    "sandbox",
    "schema-display",
    "snippet",
    "stack-trace",
    "task",
    "terminal",
    "test-results",
    "transcription",
    "voice-selector",
    "web-preview"
  ],
  "components": [
    {
      "slug": "agent",
      "slug_guess": "agent",
      "path": "src/components/ai-elements/agent.tsx",
      "exports_found": [
        "AgentCardProps",
        "AgentCard",
        "AgentHeaderProps",
        "AgentHeader",
        "AgentContentProps",
        "AgentContent",
        "AgentInstructionsProps",
        "AgentInstructions",
        "AgentToolsProps",
        "AgentTools",
        "AgentToolProps",
        "AgentTool",
        "AgentOutputProps",
        "AgentOutput"
      ],
      "has_default_export": false,
      "notes": "",
      "exported_from_index": true
    },
    {
      "slug": "artifact-panel",
      "slug_guess": "artifact-panel",
      "path": "src/components/ai-elements/artifact-panel.tsx",
      "exports_found": [
        "ArtifactPanel"
      ],
      "has_default_export": false,
      "notes": "",
      "exported_from_index": true
    },
    {
      "slug": "artifact",
      "slug_guess": "artifact",
      "path": "src/components/ai-elements/artifact.tsx",
      "exports_found": [
        "ArtifactProps",
        "Artifact",
        "ArtifactHeaderProps",
        "ArtifactHeader",
        "ArtifactCloseProps",
        "ArtifactClose",
        "ArtifactTitleProps",
        "ArtifactTitle",
        "ArtifactDescriptionProps",
        "ArtifactDescription",
        "ArtifactActionsProps",
        "ArtifactActions",
        "ArtifactActionProps",
        "ArtifactAction",
        "ArtifactContentProps",
        "ArtifactContent"
      ],
      "has_default_export": false,
      "notes": "",
      "exported_from_index": true
    },
    {
      "slug": "attachments",
      "slug_guess": "attachments",
      "path": "src/components/ai-elements/attachments.tsx",
      "exports_found": [
        "AttachmentData",
        "AttachmentMediaCategory",
        "AttachmentVariant",
        "getMediaCategory",
        "getAttachmentLabel",
        "useAttachmentsContext",
        "useAttachmentContext",
        "AttachmentsProps",
        "Attachments",
        "AttachmentProps",
        "Attachment",
        "AttachmentPreviewProps",
        "AttachmentPreview",
        "AttachmentInfoProps",
        "AttachmentInfo",
        "AttachmentRemoveProps",
        "AttachmentRemove",
        "AttachmentHoverCardProps",
        "AttachmentHoverCard",
        "AttachmentHoverCardTriggerProps",
        "AttachmentHoverCardTrigger",
        "AttachmentHoverCardContentProps",
        "AttachmentHoverCardContent",
        "AttachmentEmptyProps",
        "AttachmentEmpty"
      ],
      "has_default_export": false,
      "notes": "",
      "exported_from_index": true
    },
    {
      "slug": "audio-player",
      "slug_guess": "audio-player",
      "path": "src/components/ai-elements/audio-player.tsx",
      "exports_found": [
        "AudioPlayerProps",
        "AudioPlayer",
        "AudioPlayerElementProps",
        "AudioPlayerElement",
        "AudioPlayerControlBarProps",
        "AudioPlayerControlBar",
        "AudioPlayerPlayButtonProps",
        "AudioPlayerPlayButton",
        "AudioPlayerSeekBackwardButtonProps",
        "AudioPlayerSeekBackwardButton",
        "AudioPlayerSeekForwardButtonProps",
        "AudioPlayerSeekForwardButton",
        "AudioPlayerTimeDisplayProps",
        "AudioPlayerTimeDisplay",
        "AudioPlayerTimeRangeProps",
        "AudioPlayerTimeRange",
        "AudioPlayerDurationDisplayProps",
        "AudioPlayerDurationDisplay",
        "AudioPlayerMuteButtonProps",
        "AudioPlayerMuteButton",
        "AudioPlayerVolumeRangeProps",
        "AudioPlayerVolumeRange"
      ],
      "has_default_export": false,
      "notes": "",
      "exported_from_index": true
    },
    {
      "slug": "canvas",
      "slug_guess": "canvas",
      "path": "src/components/ai-elements/canvas.tsx",
      "exports_found": [
        "Canvas"
      ],
      "has_default_export": false,
      "notes": "",
      "exported_from_index": true
    },
    {
      "slug": "chain-of-thought",
      "slug_guess": "chain-of-thought",
      "path": "src/components/ai-elements/chain-of-thought.tsx",
      "exports_found": [
        "ChainOfThoughtProps",
        "ChainOfThought",
        "ChainOfThoughtHeaderProps",
        "ChainOfThoughtHeader",
        "ChainOfThoughtStepProps",
        "ChainOfThoughtStep",
        "ChainOfThoughtSearchResultsProps",
        "ChainOfThoughtSearchResults",
        "ChainOfThoughtSearchResultProps",
        "ChainOfThoughtSearchResult",
        "ChainOfThoughtContentProps",
        "ChainOfThoughtContent",
        "ChainOfThoughtImageProps",
        "ChainOfThoughtImage"
      ],
      "has_default_export": false,
      "notes": "",
      "exported_from_index": true
    },
    {
      "slug": "checkpoint",
      "slug_guess": "checkpoint",
      "path": "src/components/ai-elements/checkpoint.tsx",
      "exports_found": [
        "CheckpointProps",
        "Checkpoint",
        "CheckpointIconProps",
        "CheckpointIcon",
        "CheckpointTriggerProps",
        "CheckpointTrigger"
      ],
      "has_default_export": false,
      "notes": "",
      "exported_from_index": true
    },
    {
      "slug": "code-block",
      "slug_guess": "code-block",
      "path": "src/components/ai-elements/code-block.tsx",
      "exports_found": [
        "highlightCode",
        "CodeBlockContainer",
        "CodeBlockHeader",
        "CodeBlockTitle",
        "CodeBlockFilename",
        "CodeBlockActions",
        "CodeBlockContent",
        "CodeBlock",
        "CodeBlockCopyButtonProps",
        "CodeBlockCopyButton",
        "CodeBlockLanguageSelectorProps",
        "CodeBlockLanguageSelector",
        "CodeBlockLanguageSelectorTriggerProps",
        "CodeBlockLanguageSelectorTrigger",
        "CodeBlockLanguageSelectorValueProps",
        "CodeBlockLanguageSelectorValue",
        "CodeBlockLanguageSelectorContentProps",
        "CodeBlockLanguageSelectorContent",
        "CodeBlockLanguageSelectorItemProps",
        "CodeBlockLanguageSelectorItem"
      ],
      "has_default_export": false,
      "notes": "",
      "exported_from_index": true
    },
    {
      "slug": "commit",
      "slug_guess": "commit",
      "path": "src/components/ai-elements/commit.tsx",
      "exports_found": [
        "CommitProps",
        "Commit",
        "CommitHeaderProps",
        "CommitHeader",
        "CommitHashProps",
        "CommitHash",
        "CommitMessageProps",
        "CommitMessage",
        "CommitMetadataProps",
        "CommitMetadata",
        "CommitSeparatorProps",
        "CommitSeparator",
        "CommitInfoProps",
        "CommitInfo",
        "CommitAuthorProps",
        "CommitAuthor",
        "CommitAuthorAvatarProps",
        "CommitAuthorAvatar",
        "CommitTimestampProps",
        "CommitTimestamp",
        "CommitActionsProps",
        "CommitActions",
        "CommitCopyButtonProps",
        "CommitCopyButton",
        "CommitContentProps",
        "CommitContent",
        "CommitFilesProps",
        "CommitFiles",
        "CommitFileProps",
        "CommitFile",
        "CommitFileInfoProps",
        "CommitFileInfo",
        "CommitFileStatusProps",
        "CommitFileStatus",
        "CommitFileIconProps",
        "CommitFileIcon",
        "CommitFilePathProps",
        "CommitFilePath",
        "CommitFileChangesProps",
        "CommitFileChanges",
        "CommitFileAdditionsProps",
        "CommitFileAdditions",
        "CommitFileDeletionsProps",
        "CommitFileDeletions"
      ],
      "has_default_export": false,
      "notes": "",
      "exported_from_index": true
    },
    {
      "slug": "confirmation",
      "slug_guess": "confirmation",
      "path": "src/components/ai-elements/confirmation.tsx",
      "exports_found": [
        "ConfirmationProps",
        "Confirmation",
        "ConfirmationTitleProps",
        "ConfirmationTitle",
        "ConfirmationRequestProps",
        "ConfirmationRequest",
        "ConfirmationAcceptedProps",
        "ConfirmationAccepted",
        "ConfirmationRejectedProps",
        "ConfirmationRejected",
        "ConfirmationActionsProps",
        "ConfirmationActions",
        "ConfirmationActionProps",
        "ConfirmationAction"
      ],
      "has_default_export": false,
      "notes": "",
      "exported_from_index": true
    },
    {
      "slug": "connection",
      "slug_guess": "connection",
      "path": "src/components/ai-elements/connection.tsx",
      "exports_found": [
        "Connection"
      ],
      "has_default_export": false,
      "notes": "",
      "exported_from_index": true
    },
    {
      "slug": "context",
      "slug_guess": "context",
      "path": "src/components/ai-elements/context.tsx",
      "exports_found": [
        "ContextProps",
        "Context",
        "ContextTriggerProps",
        "ContextTrigger",
        "ContextContentProps",
        "ContextContent",
        "ContextContentHeaderProps",
        "ContextContentHeader",
        "ContextContentBodyProps",
        "ContextContentBody",
        "ContextContentFooterProps",
        "ContextContentFooter",
        "ContextInputUsageProps",
        "ContextInputUsage",
        "ContextOutputUsageProps",
        "ContextOutputUsage",
        "ContextReasoningUsageProps",
        "ContextReasoningUsage",
        "ContextCacheUsageProps",
        "ContextCacheUsage"
      ],
      "has_default_export": false,
      "notes": "",
      "exported_from_index": true
    },
    {
      "slug": "controls",
      "slug_guess": "controls",
      "path": "src/components/ai-elements/controls.tsx",
      "exports_found": [
        "ControlsProps",
        "Controls"
      ],
      "has_default_export": false,
      "notes": "",
      "exported_from_index": true
    },
    {
      "slug": "conversation",
      "slug_guess": "conversation",
      "path": "src/components/ai-elements/conversation.tsx",
      "exports_found": [
        "ConversationProps",
        "Conversation",
        "ConversationContentProps",
        "ConversationContent",
        "ConversationEmptyStateProps",
        "ConversationEmptyState",
        "ConversationScrollButtonProps",
        "ConversationScrollButton",
        "ConversationMessage",
        "ConversationDownloadProps",
        "messagesToMarkdown",
        "ConversationDownload"
      ],
      "has_default_export": false,
      "notes": "",
      "exported_from_index": true
    },
    {
      "slug": "edge",
      "slug_guess": "edge",
      "path": "src/components/ai-elements/edge.tsx",
      "exports_found": [
        "Edge"
      ],
      "has_default_export": false,
      "notes": "",
      "exported_from_index": true
    },
    {
      "slug": "environment-variables",
      "slug_guess": "environment-variables",
      "path": "src/components/ai-elements/environment-variables.tsx",
      "exports_found": [
        "EnvironmentVariablesProps",
        "EnvironmentVariables",
        "EnvironmentVariablesHeaderProps",
        "EnvironmentVariablesHeader",
        "EnvironmentVariablesTitleProps",
        "EnvironmentVariablesTitle",
        "EnvironmentVariablesToggleProps",
        "EnvironmentVariablesToggle",
        "EnvironmentVariablesContentProps",
        "EnvironmentVariablesContent",
        "EnvironmentVariableProps",
        "EnvironmentVariable",
        "EnvironmentVariableGroupProps",
        "EnvironmentVariableGroup",
        "EnvironmentVariableNameProps",
        "EnvironmentVariableName",
        "EnvironmentVariableValueProps",
        "EnvironmentVariableValue",
        "EnvironmentVariableCopyButtonProps",
        "EnvironmentVariableCopyButton",
        "EnvironmentVariableRequiredProps",
        "EnvironmentVariableRequired"
      ],
      "has_default_export": false,
      "notes": "",
      "exported_from_index": true
    },
    {
      "slug": "file-tree",
      "slug_guess": "file-tree",
      "path": "src/components/ai-elements/file-tree.tsx",
      "exports_found": [
        "FileTreeProps",
        "FileTree",
        "FileTreeFolderProps",
        "FileTreeFolder",
        "FileTreeFileProps",
        "FileTreeFile",
        "FileTreeIconProps",
        "FileTreeIcon",
        "FileTreeNameProps",
        "FileTreeName",
        "FileTreeActionsProps",
        "FileTreeActions"
      ],
      "has_default_export": false,
      "notes": "",
      "exported_from_index": true
    },
    {
      "slug": "image",
      "slug_guess": "image",
      "path": "src/components/ai-elements/image.tsx",
      "exports_found": [
        "ImageProps",
        "Image"
      ],
      "has_default_export": false,
      "notes": "",
      "exported_from_index": true
    },
    {
      "slug": "inline-citation",
      "slug_guess": "inline-citation",
      "path": "src/components/ai-elements/inline-citation.tsx",
      "exports_found": [
        "InlineCitationProps",
        "InlineCitation",
        "InlineCitationTextProps",
        "InlineCitationText",
        "InlineCitationCardProps",
        "InlineCitationCard",
        "InlineCitationCardTriggerProps",
        "InlineCitationCardTrigger",
        "InlineCitationCardBodyProps",
        "InlineCitationCardBody",
        "InlineCitationCarouselProps",
        "InlineCitationCarousel",
        "InlineCitationCarouselContentProps",
        "InlineCitationCarouselContent",
        "InlineCitationCarouselItemProps",
        "InlineCitationCarouselItem",
        "InlineCitationCarouselHeaderProps",
        "InlineCitationCarouselHeader",
        "InlineCitationCarouselIndexProps",
        "InlineCitationCarouselIndex",
        "InlineCitationCarouselPrevProps",
        "InlineCitationCarouselPrev",
        "InlineCitationCarouselNextProps",
        "InlineCitationCarouselNext",
        "InlineCitationSourceProps",
        "InlineCitationSource",
        "InlineCitationQuoteProps",
        "InlineCitationQuote"
      ],
      "has_default_export": false,
      "notes": "",
      "exported_from_index": true
    },
    {
      "slug": "jsx-preview",
      "slug_guess": "jsx-preview",
      "path": "src/components/ai-elements/jsx-preview.tsx",
      "exports_found": [
        "useJSXPreview",
        "JSXPreviewProps",
        "JSXPreview",
        "JSXPreviewContentProps",
        "JSXPreviewContent",
        "JSXPreviewErrorProps",
        "JSXPreviewError"
      ],
      "has_default_export": false,
      "notes": "",
      "exported_from_index": true
    },
    {
      "slug": "markdown",
      "slug_guess": "markdown",
      "path": "src/components/ai-elements/markdown.tsx",
      "exports_found": [
        "Markdown"
      ],
      "has_default_export": false,
      "notes": "",
      "exported_from_index": true
    },
    {
      "slug": "message",
      "slug_guess": "message",
      "path": "src/components/ai-elements/message.tsx",
      "exports_found": [
        "MessageProps",
        "Message",
        "MessageContentProps",
        "MessageContent",
        "MessageActionsProps",
        "MessageActions",
        "MessageActionProps",
        "MessageAction",
        "MessageBranchProps",
        "MessageBranch",
        "MessageBranchContentProps",
        "MessageBranchContent",
        "MessageBranchSelectorProps",
        "MessageBranchSelector",
        "MessageBranchPreviousProps",
        "MessageBranchPrevious",
        "MessageBranchNextProps",
        "MessageBranchNext",
        "MessageBranchPageProps",
        "MessageBranchPage",
        "MessageResponseProps",
        "MessageResponse",
        "MessageToolbarProps",
        "MessageToolbar"
      ],
      "has_default_export": false,
      "notes": "",
      "exported_from_index": true
    },
    {
      "slug": "mic-selector",
      "slug_guess": "mic-selector",
      "path": "src/components/ai-elements/mic-selector.tsx",
      "exports_found": [
        "MicSelectorProps",
        "MicSelector",
        "MicSelectorTriggerProps",
        "MicSelectorTrigger",
        "MicSelectorContentProps",
        "MicSelectorContent",
        "MicSelectorInputProps",
        "MicSelectorInput",
        "MicSelectorListProps",
        "MicSelectorList",
        "MicSelectorEmptyProps",
        "MicSelectorEmpty",
        "MicSelectorItemProps",
        "MicSelectorItem",
        "MicSelectorLabelProps",
        "MicSelectorLabel",
        "MicSelectorValueProps",
        "MicSelectorValue",
        "useAudioDevices"
      ],
      "has_default_export": false,
      "notes": "",
      "exported_from_index": true
    },
    {
      "slug": "model-selector",
      "slug_guess": "model-selector",
      "path": "src/components/ai-elements/model-selector.tsx",
      "exports_found": [
        "ModelSelectorProps",
        "ModelSelector",
        "ModelSelectorTriggerProps",
        "ModelSelectorTrigger",
        "ModelSelectorContentProps",
        "ModelSelectorContent",
        "ModelSelectorDialogProps",
        "ModelSelectorDialog",
        "ModelSelectorInputProps",
        "ModelSelectorInput",
        "ModelSelectorListProps",
        "ModelSelectorList",
        "ModelSelectorEmptyProps",
        "ModelSelectorEmpty",
        "ModelSelectorGroupProps",
        "ModelSelectorGroup",
        "ModelSelectorItemProps",
        "ModelSelectorItem",
        "ModelSelectorShortcutProps",
        "ModelSelectorShortcut",
        "ModelSelectorSeparatorProps",
        "ModelSelectorSeparator",
        "ModelSelectorLogoProps",
        "ModelSelectorLogo",
        "ModelSelectorLogoGroupProps",
        "ModelSelectorLogoGroup",
        "ModelSelectorNameProps",
        "ModelSelectorName"
      ],
      "has_default_export": false,
      "notes": "",
      "exported_from_index": true
    },
    {
      "slug": "node",
      "slug_guess": "node",
      "path": "src/components/ai-elements/node.tsx",
      "exports_found": [
        "NodeProps",
        "Node",
        "NodeHeaderProps",
        "NodeHeader",
        "NodeTitleProps",
        "NodeTitle",
        "NodeDescriptionProps",
        "NodeDescription",
        "NodeActionProps",
        "NodeAction",
        "NodeContentProps",
        "NodeContent",
        "NodeFooterProps",
        "NodeFooter"
      ],
      "has_default_export": false,
      "notes": "",
      "exported_from_index": true
    },
    {
      "slug": "open-in-chat",
      "slug_guess": "open-in-chat",
      "path": "src/components/ai-elements/open-in-chat.tsx",
      "exports_found": [
        "OpenInProps",
        "OpenIn",
        "OpenInContentProps",
        "OpenInContent",
        "OpenInItemProps",
        "OpenInItem",
        "OpenInLabelProps",
        "OpenInLabel",
        "OpenInSeparatorProps",
        "OpenInSeparator",
        "OpenInTriggerProps",
        "OpenInTrigger",
        "OpenInChatGPTProps",
        "OpenInChatGPT",
        "OpenInClaudeProps",
        "OpenInClaude",
        "OpenInT3Props",
        "OpenInT3",
        "OpenInSciraProps",
        "OpenInScira",
        "OpenInv0Props",
        "OpenInv0",
        "OpenInCursorProps",
        "OpenInCursor"
      ],
      "has_default_export": false,
      "notes": "",
      "exported_from_index": true
    },
    {
      "slug": "package-info",
      "slug_guess": "package-info",
      "path": "src/components/ai-elements/package-info.tsx",
      "exports_found": [
        "PackageInfoProps",
        "PackageInfo",
        "PackageInfoHeaderProps",
        "PackageInfoHeader",
        "PackageInfoNameProps",
        "PackageInfoName",
        "PackageInfoChangeTypeProps",
        "PackageInfoChangeType",
        "PackageInfoVersionProps",
        "PackageInfoVersion",
        "PackageInfoDescriptionProps",
        "PackageInfoDescription",
        "PackageInfoContentProps",
        "PackageInfoContent",
        "PackageInfoDependenciesProps",
        "PackageInfoDependencies",
        "PackageInfoDependencyProps",
        "PackageInfoDependency"
      ],
      "has_default_export": false,
      "notes": "",
      "exported_from_index": true
    },
    {
      "slug": "panel",
      "slug_guess": "panel",
      "path": "src/components/ai-elements/panel.tsx",
      "exports_found": [
        "Panel"
      ],
      "has_default_export": false,
      "notes": "",
      "exported_from_index": true
    },
    {
      "slug": "persona",
      "slug_guess": "persona",
      "path": "src/components/ai-elements/persona.tsx",
      "exports_found": [
        "PersonaState",
        "Persona"
      ],
      "has_default_export": false,
      "notes": "",
      "exported_from_index": true
    },
    {
      "slug": "plan",
      "slug_guess": "plan",
      "path": "src/components/ai-elements/plan.tsx",
      "exports_found": [
        "PlanProps",
        "Plan",
        "PlanHeaderProps",
        "PlanHeader",
        "PlanTitleProps",
        "PlanTitle",
        "PlanDescriptionProps",
        "PlanDescription",
        "PlanActionProps",
        "PlanAction",
        "PlanContentProps",
        "PlanContent",
        "PlanFooterProps",
        "PlanFooter",
        "PlanTriggerProps",
        "PlanTrigger"
      ],
      "has_default_export": false,
      "notes": "",
      "exported_from_index": true
    },
    {
      "slug": "prompt-input",
      "slug_guess": "prompt-input",
      "path": "src/components/ai-elements/prompt-input.tsx",
      "exports_found": [
        "AttachmentsContext",
        "TextInputContext",
        "PromptInputControllerProps",
        "usePromptInputController",
        "useProviderAttachments",
        "PromptInputProviderProps",
        "PromptInputProvider",
        "usePromptInputAttachments",
        "ReferencedSourcesContext",
        "LocalReferencedSourcesContext",
        "usePromptInputReferencedSources",
        "PromptInputActionAddAttachmentsProps",
        "PromptInputActionAddAttachments",
        "PromptInputMessage",
        "PromptInputProps",
        "PromptInput",
        "PromptInputBodyProps",
        "PromptInputBody",
        "PromptInputTextareaProps",
        "PromptInputTextarea",
        "PromptInputHeaderProps",
        "PromptInputHeader",
        "PromptInputFooterProps",
        "PromptInputFooter",
        "PromptInputToolsProps",
        "PromptInputTools",
        "PromptInputButtonTooltip",
        "PromptInputButtonProps",
        "PromptInputButton",
        "PromptInputActionMenuProps",
        "PromptInputActionMenu",
        "PromptInputActionMenuTriggerProps",
        "PromptInputActionMenuTrigger",
        "PromptInputActionMenuContentProps",
        "PromptInputActionMenuContent",
        "PromptInputActionMenuItemProps",
        "PromptInputActionMenuItem",
        "PromptInputSubmitProps",
        "PromptInputSubmit",
        "PromptInputSelectProps",
        "PromptInputSelect",
        "PromptInputSelectTriggerProps",
        "PromptInputSelectTrigger",
        "PromptInputSelectContentProps",
        "PromptInputSelectContent",
        "PromptInputSelectItemProps",
        "PromptInputSelectItem",
        "PromptInputSelectValueProps",
        "PromptInputSelectValue",
        "PromptInputHoverCardProps",
        "PromptInputHoverCard",
        "PromptInputHoverCardTriggerProps",
        "PromptInputHoverCardTrigger",
        "PromptInputHoverCardContentProps",
        "PromptInputHoverCardContent",
        "PromptInputTabsListProps",
        "PromptInputTabsList",
        "PromptInputTabProps",
        "PromptInputTab",
        "PromptInputTabLabelProps",
        "PromptInputTabLabel",
        "PromptInputTabBodyProps",
        "PromptInputTabBody",
        "PromptInputTabItemProps",
        "PromptInputTabItem",
        "PromptInputCommandProps",
        "PromptInputCommand",
        "PromptInputCommandInputProps",
        "PromptInputCommandInput",
        "PromptInputCommandListProps",
        "PromptInputCommandList",
        "PromptInputCommandEmptyProps",
        "PromptInputCommandEmpty",
        "PromptInputCommandGroupProps",
        "PromptInputCommandGroup",
        "PromptInputCommandItemProps",
        "PromptInputCommandItem",
        "PromptInputCommandSeparatorProps",
        "PromptInputCommandSeparator"
      ],
      "has_default_export": false,
      "notes": "",
      "exported_from_index": true
    },
    {
      "slug": "queue",
      "slug_guess": "queue",
      "path": "src/components/ai-elements/queue.tsx",
      "exports_found": [
        "QueueMessagePart",
        "QueueMessage",
        "QueueTodo",
        "QueueItemProps",
        "QueueItem",
        "QueueItemIndicatorProps",
        "QueueItemIndicator",
        "QueueItemContentProps",
        "QueueItemContent",
        "QueueItemDescriptionProps",
        "QueueItemDescription",
        "QueueItemActionsProps",
        "QueueItemActions",
        "QueueItemActionProps",
        "QueueItemAction",
        "QueueItemAttachmentProps",
        "QueueItemAttachment",
        "QueueItemImageProps",
        "QueueItemImage",
        "QueueItemFileProps",
        "QueueItemFile",
        "QueueListProps",
        "QueueList",
        "QueueSectionProps",
        "QueueSection",
        "QueueSectionTriggerProps",
        "QueueSectionTrigger",
        "QueueSectionLabelProps",
        "QueueSectionLabel",
        "QueueSectionContentProps",
        "QueueSectionContent",
        "QueueProps",
        "Queue"
      ],
      "has_default_export": false,
      "notes": "",
      "exported_from_index": true
    },
    {
      "slug": "reasoning",
      "slug_guess": "reasoning",
      "path": "src/components/ai-elements/reasoning.tsx",
      "exports_found": [
        "useReasoning",
        "ReasoningProps",
        "Reasoning",
        "ReasoningTriggerProps",
        "ReasoningTrigger",
        "ReasoningContentProps",
        "ReasoningContent"
      ],
      "has_default_export": false,
      "notes": "",
      "exported_from_index": true
    },
    {
      "slug": "sandbox",
      "slug_guess": "sandbox",
      "path": "src/components/ai-elements/sandbox.tsx",
      "exports_found": [
        "SandboxRootProps",
        "Sandbox",
        "SandboxHeaderProps",
        "SandboxHeader",
        "SandboxContentProps",
        "SandboxContent",
        "SandboxTabsProps",
        "SandboxTabs",
        "SandboxTabsBarProps",
        "SandboxTabsBar",
        "SandboxTabsListProps",
        "SandboxTabsList",
        "SandboxTabsTriggerProps",
        "SandboxTabsTrigger",
        "SandboxTabContentProps",
        "SandboxTabContent"
      ],
      "has_default_export": false,
      "notes": "",
      "exported_from_index": true
    },
    {
      "slug": "schema-display",
      "slug_guess": "schema-display",
      "path": "src/components/ai-elements/schema-display.tsx",
      "exports_found": [
        "SchemaDisplayProps",
        "SchemaDisplay",
        "SchemaDisplayHeaderProps",
        "SchemaDisplayHeader",
        "SchemaDisplayMethodProps",
        "SchemaDisplayMethod",
        "SchemaDisplayPathProps",
        "SchemaDisplayPath",
        "SchemaDisplayDescriptionProps",
        "SchemaDisplayDescription",
        "SchemaDisplayContentProps",
        "SchemaDisplayContent",
        "SchemaDisplayParametersProps",
        "SchemaDisplayParameters",
        "SchemaDisplayParameterProps",
        "SchemaDisplayParameter",
        "SchemaDisplayRequestProps",
        "SchemaDisplayRequest",
        "SchemaDisplayResponseProps",
        "SchemaDisplayResponse",
        "SchemaDisplayBodyProps",
        "SchemaDisplayBody",
        "SchemaDisplayPropertyProps",
        "SchemaDisplayProperty",
        "SchemaDisplayExampleProps",
        "SchemaDisplayExample"
      ],
      "has_default_export": false,
      "notes": "",
      "exported_from_index": true
    },
    {
      "slug": "shimmer",
      "slug_guess": "shimmer",
      "path": "src/components/ai-elements/shimmer.tsx",
      "exports_found": [
        "TextShimmerProps",
        "Shimmer"
      ],
      "has_default_export": false,
      "notes": "",
      "exported_from_index": true
    },
    {
      "slug": "snippet",
      "slug_guess": "snippet",
      "path": "src/components/ai-elements/snippet.tsx",
      "exports_found": [
        "SnippetProps",
        "Snippet",
        "SnippetAddonProps",
        "SnippetAddon",
        "SnippetTextProps",
        "SnippetText",
        "SnippetInputProps",
        "SnippetInput",
        "SnippetCopyButtonProps",
        "SnippetCopyButton"
      ],
      "has_default_export": false,
      "notes": "",
      "exported_from_index": true
    },
    {
      "slug": "sources",
      "slug_guess": "sources",
      "path": "src/components/ai-elements/sources.tsx",
      "exports_found": [
        "SourcesProps",
        "Sources",
        "SourcesTriggerProps",
        "SourcesTrigger",
        "SourcesContentProps",
        "SourcesContent",
        "SourceProps",
        "Source"
      ],
      "has_default_export": false,
      "notes": "",
      "exported_from_index": true
    },
    {
      "slug": "speech-input",
      "slug_guess": "speech-input",
      "path": "src/components/ai-elements/speech-input.tsx",
      "exports_found": [
        "SpeechInputProps",
        "SpeechInput"
      ],
      "has_default_export": false,
      "notes": "",
      "exported_from_index": true
    },
    {
      "slug": "stack-trace",
      "slug_guess": "stack-trace",
      "path": "src/components/ai-elements/stack-trace.tsx",
      "exports_found": [
        "StackTraceProps",
        "StackTrace",
        "StackTraceHeaderProps",
        "StackTraceHeader",
        "StackTraceErrorProps",
        "StackTraceError",
        "StackTraceErrorTypeProps",
        "StackTraceErrorType",
        "StackTraceErrorMessageProps",
        "StackTraceErrorMessage",
        "StackTraceActionsProps",
        "StackTraceActions",
        "StackTraceCopyButtonProps",
        "StackTraceCopyButton",
        "StackTraceExpandButtonProps",
        "StackTraceExpandButton",
        "StackTraceContentProps",
        "StackTraceContent",
        "StackTraceFramesProps",
        "StackTraceFrames"
      ],
      "has_default_export": false,
      "notes": "",
      "exported_from_index": true
    },
    {
      "slug": "suggestion",
      "slug_guess": "suggestion",
      "path": "src/components/ai-elements/suggestion.tsx",
      "exports_found": [
        "SuggestionsProps",
        "Suggestions",
        "SuggestionProps",
        "Suggestion"
      ],
      "has_default_export": false,
      "notes": "",
      "exported_from_index": true
    },
    {
      "slug": "task",
      "slug_guess": "task",
      "path": "src/components/ai-elements/task.tsx",
      "exports_found": [
        "TaskItemFileProps",
        "TaskItemFile",
        "TaskItemProps",
        "TaskItem",
        "TaskProps",
        "Task",
        "TaskTriggerProps",
        "TaskTrigger",
        "TaskContentProps",
        "TaskContent"
      ],
      "has_default_export": false,
      "notes": "",
      "exported_from_index": true
    },
    {
      "slug": "terminal",
      "slug_guess": "terminal",
      "path": "src/components/ai-elements/terminal.tsx",
      "exports_found": [
        "TerminalProps",
        "Terminal",
        "TerminalHeaderProps",
        "TerminalHeader",
        "TerminalTitleProps",
        "TerminalTitle",
        "TerminalStatusProps",
        "TerminalStatus",
        "TerminalActionsProps",
        "TerminalActions",
        "TerminalCopyButtonProps",
        "TerminalCopyButton",
        "TerminalClearButtonProps",
        "TerminalClearButton",
        "TerminalContentProps",
        "TerminalContent"
      ],
      "has_default_export": false,
      "notes": "",
      "exported_from_index": true
    },
    {
      "slug": "test-results",
      "slug_guess": "test-results",
      "path": "src/components/ai-elements/test-results.tsx",
      "exports_found": [
        "TestResultsProps",
        "TestResults",
        "TestResultsHeaderProps",
        "TestResultsHeader",
        "TestResultsSummaryProps",
        "TestResultsSummary",
        "TestResultsDurationProps",
        "TestResultsDuration",
        "TestResultsProgressProps",
        "TestResultsProgress",
        "TestResultsContentProps",
        "TestResultsContent",
        "TestSuiteProps",
        "TestSuite",
        "TestSuiteNameProps",
        "TestSuiteName",
        "TestSuiteStatsProps",
        "TestSuiteStats",
        "TestSuiteContentProps",
        "TestSuiteContent",
        "TestProps",
        "Test",
        "TestStatusProps",
        "TestStatus",
        "TestNameProps",
        "TestName",
        "TestDurationProps",
        "TestDuration",
        "TestErrorProps",
        "TestError",
        "TestErrorMessageProps",
        "TestErrorMessage",
        "TestErrorStackProps",
        "TestErrorStack"
      ],
      "has_default_export": false,
      "notes": "",
      "exported_from_index": true
    },
    {
      "slug": "tool",
      "slug_guess": "tool",
      "path": "src/components/ai-elements/tool.tsx",
      "exports_found": [
        "ToolProps",
        "Tool",
        "ToolPart",
        "ToolHeaderProps",
        "getStatusBadge",
        "ToolHeader",
        "ToolContentProps",
        "ToolContent",
        "ToolInputProps",
        "ToolInput",
        "ToolOutputProps",
        "ToolOutput"
      ],
      "has_default_export": false,
      "notes": "",
      "exported_from_index": true
    },
    {
      "slug": "toolbar",
      "slug_guess": "toolbar",
      "path": "src/components/ai-elements/toolbar.tsx",
      "exports_found": [
        "Toolbar"
      ],
      "has_default_export": false,
      "notes": "",
      "exported_from_index": true
    },
    {
      "slug": "transcription",
      "slug_guess": "transcription",
      "path": "src/components/ai-elements/transcription.tsx",
      "exports_found": [
        "TranscriptionProps",
        "Transcription",
        "TranscriptionSegmentProps",
        "TranscriptionSegment"
      ],
      "has_default_export": false,
      "notes": "",
      "exported_from_index": true
    },
    {
      "slug": "voice-selector",
      "slug_guess": "voice-selector",
      "path": "src/components/ai-elements/voice-selector.tsx",
      "exports_found": [
        "useVoiceSelector",
        "VoiceSelectorProps",
        "VoiceSelector",
        "VoiceSelectorTriggerProps",
        "VoiceSelectorTrigger",
        "VoiceSelectorContentProps",
        "VoiceSelectorContent",
        "VoiceSelectorDialogProps",
        "VoiceSelectorDialog",
        "VoiceSelectorInputProps",
        "VoiceSelectorInput",
        "VoiceSelectorListProps",
        "VoiceSelectorList",
        "VoiceSelectorEmptyProps",
        "VoiceSelectorEmpty",
        "VoiceSelectorGroupProps",
        "VoiceSelectorGroup",
        "VoiceSelectorItemProps",
        "VoiceSelectorItem",
        "VoiceSelectorShortcutProps",
        "VoiceSelectorShortcut",
        "VoiceSelectorSeparatorProps",
        "VoiceSelectorSeparator",
        "VoiceSelectorGenderProps",
        "VoiceSelectorGender",
        "VoiceSelectorAccentProps",
        "VoiceSelectorAccent",
        "VoiceSelectorAgeProps",
        "VoiceSelectorAge",
        "VoiceSelectorNameProps",
        "VoiceSelectorName",
        "VoiceSelectorDescriptionProps",
        "VoiceSelectorDescription",
        "VoiceSelectorAttributesProps",
        "VoiceSelectorAttributes",
        "VoiceSelectorBulletProps",
        "VoiceSelectorBullet",
        "VoiceSelectorPreviewProps",
        "VoiceSelectorPreview"
      ],
      "has_default_export": false,
      "notes": "",
      "exported_from_index": true
    },
    {
      "slug": "web-preview",
      "slug_guess": "web-preview",
      "path": "src/components/ai-elements/web-preview.tsx",
      "exports_found": [
        "WebPreviewContextValue",
        "WebPreviewProps",
        "WebPreview",
        "WebPreviewNavigationProps",
        "WebPreviewNavigation",
        "WebPreviewNavigationButtonProps",
        "WebPreviewNavigationButton",
        "WebPreviewUrlProps",
        "WebPreviewUrl",
        "WebPreviewBodyProps",
        "WebPreviewBody",
        "WebPreviewConsoleProps",
        "WebPreviewConsole"
      ],
      "has_default_export": false,
      "notes": "",
      "exported_from_index": true
    }
  ]
}